<ROOT>
  <S>
    <NP>
      <JJ>
        <Valid/>
      </JJ>
      <NNS>
        <credentials/>
      </NNS>
    </NP>
    <VP>
      <MD>
        <must/>
      </MD>
      <VP>
        <VB>
          <be/>
        </VB>
        <VP>
          <VBN>
            <used/>
          </VBN>
          <S>
            <VP>
              <TO>
                <to/>
              </TO>
              <VP>
                <VB>
                  <gain/>
                </VB>
                <NP>
                  <VBN>
                    <required/>
                  </VBN>
                  <NN>
                    <access/>
                  </NN>
                </NP>
                <PP>
                  <TO>
                    <to/>
                  </TO>
                  <NP>
                    <NP>
                      <DT>
                        <the/>
                      </DT>
                      <NNP>
                        <AD/>
                      </NNP>
                      <NN>
                        <system/>
                      </NN>
                    </NP>
                    <,>
                      <,/>
                    </,>
                    <NP>
                      <NP>
                        <NN>
                          <standard/>
                        </NN>
                      </NP>
                      <PRN>
                        <-LRB->
                          <-LRB-/>
                        </-LRB->
                        <NP>
                          <NN>
                            <non-admin/>
                          </NN>
                        </NP>
                        <-RRB->
                          <-RRB-/>
                        </-RRB->
                      </PRN>
                      <SBAR>
                        <S>
                          <NP>
                            <NN>
                              <user/>
                            </NN>
                            <NNS>
                              <accounts/>
                            </NNS>
                          </NP>
                          <VP>
                            <MD>
                              <can/>
                            </MD>
                            <VP>
                              <VB>
                                <be/>
                              </VB>
                              <VP>
                                <VBN>
                                  <used/>
                                </VBN>
                              </VP>
                            </VP>
                          </VP>
                        </S>
                      </SBAR>
                    </NP>
                  </NP>
                </PP>
                <,>
                  <,/>
                </,>
                <PP>
                  <IN>
                    <under/>
                  </IN>
                  <NP>
                    <NP>
                      <JJ>
                        <normal/>
                      </JJ>
                      <NN>
                        <security/>
                      </NN>
                      <NNS>
                        <permissions/>
                      </NNS>
                    </NP>
                    <SBAR>
                      <S>
                        <NP>
                          <JJ>
                            <standard/>
                          </JJ>
                          <NNS>
                            <accounts/>
                          </NNS>
                        </NP>
                        <VP>
                          <MD>
                            <can/>
                          </MD>
                          <RB>
                            <not/>
                          </RB>
                          <VP>
                            <VB>
                              <alter/>
                            </VB>
                            <NP>
                              <NNS>
                                <data/>
                              </NNS>
                            </NP>
                            <PP>
                              <IN>
                                <without/>
                              </IN>
                              <S>
                                <VP>
                                  <VBG>
                                    <being/>
                                  </VBG>
                                  <VP>
                                    <VBN>
                                      <granted/>
                                    </VBN>
                                    <NP>
                                      <NP>
                                        <NNP>
                                          <Administrator/>
                                        </NNP>
                                      </NP>
                                      <CC>
                                        <or/>
                                      </CC>
                                      <NP>
                                        <JJ>
                                          <Special/>
                                        </JJ>
                                        <NN>
                                          <access/>
                                        </NN>
                                      </NP>
                                    </NP>
                                  </VP>
                                </VP>
                              </S>
                            </PP>
                          </VP>
                        </VP>
                      </S>
                    </SBAR>
                  </NP>
                </PP>
              </VP>
            </VP>
          </S>
        </VP>
      </VP>
    </VP>
  </S>
</ROOT>
amod(credentials-2, Valid-1)
nsubjpass(used-5, credentials-2)
xsubj(gain-7, credentials-2)
aux(used-5, must-3)
auxpass(used-5, be-4)
root(ROOT-0, used-5)
aux(gain-7, to-6)
xcomp(used-5, gain-7)
amod(access-9, required-8)
dobj(gain-7, access-9)
det(system-13, the-11)
nn(system-13, AD-12)
prep_to(gain-7, system-13)
appos(system-13, standard-15)
appos(standard-15, non-admin-17)
nn(accounts-20, user-19)
nsubjpass(used-23, accounts-20)
aux(used-23, can-21)
auxpass(used-23, be-22)
rcmod(standard-15, used-23)
amod(permissions-28, normal-26)
nn(permissions-28, security-27)
prep_under(gain-7, permissions-28)
amod(accounts-30, standard-29)
nsubj(alter-33, accounts-30)
aux(alter-33, can-31)
neg(alter-33, not-32)
rcmod(permissions-28, alter-33)
dobj(alter-33, data-34)
auxpass(granted-37, being-36)
prepc_without(alter-33, granted-37)
dobj(granted-37, Administrator-38)
amod(access-41, Special-40)
dobj(granted-37, access-41)
conj_or(Administrator-38, access-41)

