<ROOT>
  <NP>
    <NP>
      <JJ>
        <OS/>
      </JJ>
      <NN>
        <integration/>
      </NN>
      <NN>
        <share/>
      </NN>
    </NP>
    <NP>
      <NP>
        <NNS>
          <photos/>
        </NNS>
        <CC>
          <and/>
        </CC>
        <NNS>
          <videos/>
        </NNS>
      </NP>
      <PP>
        <RB>
          <straight/>
        </RB>
        <IN>
          <from/>
        </IN>
        <NP>
          <PRP>
            <your/>
          </PRP>
          <NNS>
            <devices/>
          </NNS>
          <NN>
            <gallery/>
          </NN>
        </NP>
      </PP>
    </NP>
  </NP>
</ROOT>
