<ROOT>
  <NP>
    <S>
      <SBAR>
        <IN>
          <If/>
        </IN>
        <S>
          <NP>
            <PRP>
              <you/>
            </PRP>
          </NP>
          <VP>
            <VBP>
              <have/>
            </VBP>
            <NP>
              <DT>
                <any/>
              </DT>
              <NNS>
                <questions/>
              </NNS>
            </NP>
          </VP>
        </S>
      </SBAR>
      <,>
        <,/>
      </,>
      <VP>
        <VB>
          <check/>
        </VB>
        <PRT>
          <RP>
            <out/>
          </RP>
        </PRT>
        <NP>
          <DT>
            <the/>
          </DT>
          <NN>
            <forum/>
          </NN>
        </NP>
      </VP>
    </S>
  </NP>
</ROOT>
mark(have-3, If-1)
nsubj(have-3, you-2)
advcl(check-7, have-3)
det(questions-5, any-4)
dobj(have-3, questions-5)
root(ROOT-0, check-7)
prt(check-7, out-8)
det(forum-10, the-9)
dobj(check-7, forum-10)

