<ROOT>
  <S>
    <NP>
      <NP>
        <DT>
          <All/>
        </DT>
        <NNS>
          <data/>
        </NNS>
      </NP>
      <PP>
        <VBG>
          <concerning/>
        </VBG>
        <NP>
          <NP>
            <NNS>
              <routes/>
            </NNS>
          </NP>
          <CC>
            <and/>
          </CC>
          <NP>
            <NP>
              <DT>
                <the/>
              </DT>
              <JJ>
                <actual/>
              </JJ>
              <NN>
                <user/>
              </NN>
              <POS>
              </POS>
            </NP>
            <NN>
              <position/>
            </NN>
          </NP>
        </NP>
      </PP>
    </NP>
    <VP>
      <VP>
        <VBZ>
          <is/>
        </VBZ>
        <ADVP>
          <RB>
            <only/>
          </RB>
        </ADVP>
        <VP>
          <VBN>
            <used/>
          </VBN>
          <ADVP>
            <RB>
              <internally/>
            </RB>
          </ADVP>
          <PP>
            <TO>
              <to/>
            </TO>
            <NP>
              <DT>
                <the/>
              </DT>
              <NN>
                <application/>
              </NN>
            </NP>
          </PP>
        </VP>
      </VP>
      <CC>
        <and/>
      </CC>
      <VP>
        <VBZ>
          <is/>
        </VBZ>
        <RB>
          <not/>
        </RB>
        <VP>
          <VBN>
            <shared/>
          </VBN>
          <PP>
            <IN>
              <in/>
            </IN>
            <NP>
              <DT>
                <any/>
              </DT>
              <NN>
                <way/>
              </NN>
            </NP>
          </PP>
        </VP>
      </VP>
    </VP>
  </S>
</ROOT>
