<ROOT>
  <SBAR>
    <IN>
      <While/>
    </IN>
    <S>
      <PP>
        <IN>
          <at/>
        </IN>
        <NP>
          <NP>
            <DT>
              <the/>
            </DT>
            <NN>
              <phone/>
            </NN>
            <POS>
            </POS>
          </NP>
          <NN>
            <home/>
          </NN>
          <NN>
            <screen/>
          </NN>
        </NP>
      </PP>
      <NP>
        <NP>
          <NN>
            <click/>
          </NN>
        </NP>
        <PP>
          <IN>
            <on/>
          </IN>
          <NP>
            <NP>
              <DT>
                <the/>
              </DT>
              <NNP>
                <Menu/>
              </NNP>
              <NN>
                <button/>
              </NN>
            </NP>
            <ADVP>
              <RB>
                <then/>
              </RB>
            </ADVP>
          </NP>
        </PP>
      </NP>
      <VP>
        <VBZ>
          <Settings/>
        </VBZ>
      </VP>
    </S>
  </SBAR>
</ROOT>
