<ROOT>
  <S>
    <NP>
      <NP>
        <DT>
          <The/>
        </DT>
        <NN>
          <Stop/>
        </NN>
      </NP>
      <PP>
        <IN>
          <after/>
        </IN>
        <NP>
          <JJ>
            <edit/>
          </JJ>
          <NN>
            <button/>
          </NN>
        </NP>
      </PP>
    </NP>
    <VP>
      <VBZ>
        <allows/>
      </VBZ>
      <S>
        <NP>
          <PRP>
            <you/>
          </PRP>
        </NP>
        <VP>
          <TO>
            <to/>
          </TO>
          <VP>
            <VB>
              <select/>
            </VB>
            <SBAR>
              <WHADJP>
                <WRB>
                  <how/>
                </WRB>
                <JJ>
                  <many/>
                </JJ>
              </WHADJP>
              <S>
                <NP>
                  <NN>
                    <run/>
                  </NN>
                  <NNS>
                    <XXXXX/>
                  </NNS>
                </NP>
                <VP>
                  <VBP>
                    <walk/>
                  </VBP>
                  <NP>
                    <NP>
                      <NNS>
                        <intervals/>
                      </NNS>
                    </NP>
                    <SBAR>
                      <S>
                        <NP>
                          <PRP>
                            <you/>
                          </PRP>
                        </NP>
                        <VP>
                          <VBP>
                            <want/>
                          </VBP>
                          <ADVP>
                            <RB>
                              <prior/>
                            </RB>
                            <S>
                              <VP>
                                <TO>
                                  <to/>
                                </TO>
                                <VP>
                                  <VB>
                                    <run/>
                                  </VB>
                                  <NP>
                                    <NP>
                                      <NN>
                                        <completion/>
                                      </NN>
                                    </NP>
                                    <CC>
                                      <or/>
                                    </CC>
                                    <NP>
                                      <DT>
                                        <the/>
                                      </DT>
                                      <JJ>
                                        <cool/>
                                      </JJ>
                                      <JJ>
                                        <down/>
                                      </JJ>
                                      <NN>
                                        <interval/>
                                      </NN>
                                      <NN>
                                        <firing/>
                                      </NN>
                                    </NP>
                                  </NP>
                                </VP>
                              </VP>
                            </S>
                          </ADVP>
                        </VP>
                      </S>
                    </SBAR>
                  </NP>
                </VP>
              </S>
            </SBAR>
          </VP>
        </VP>
      </S>
    </VP>
  </S>
</ROOT>
