<ROOT>
  <S>
    <NP>
      <NP>
        <NNP>
          <Start/>
        </NNP>
        <DT>
          <the/>
        </DT>
        <NNP>
          <Timer/>
        </NNP>
      </NP>
      <CC>
        <and/>
      </CC>
      <NP>
        <DT>
          <the/>
        </DT>
        <NN>
          <sound/>
        </NN>
      </NP>
    </NP>
    <VP>
      <MD>
        <should/>
      </MD>
      <VP>
        <VB>
          <work/>
        </VB>
        <ADVP>
          <RB>
            <properly/>
          </RB>
        </ADVP>
      </VP>
    </VP>
  </S>
</ROOT>
